ainfra/__init__.py
ainfra/__main__.py
ainfra/cli.py
ainfra-0.1.3.dist-info/METADATA
ainfra-0.1.3.dist-info/WHEEL
ainfra-0.1.3.dist-info/entry_points.txt
ainfra-0.1.3.dist-info/licenses/LICENSE
ainfra-0.1.3.dist-info/RECORD
